{
  "id": "3-palavrinhas-rei-davi-d3e103f1f3",
  "title": "Rei Davi",
  "artist": "3 Palavrinhas",
  "collection": "cifras_multi",
  "fileType": "html",
  "key": "D",
  "updatedAt": "2026-04-28T01:47:16.154Z",
  "html": "<u>(Riff 1)\r\n\r\n</u><b>E|------------------------------------------------------|\r\n</b><b>B|------------------------------------------------------|\r\n</b><b>G|------------------------------------------------------|\r\n</b><b>D|---------------------------------7-5------------------|\r\n</b><b>A|-5--5-5--8--5--5-5--8--5--5-5--8-----8-7-5--8--5------|\r\n</b><b>E|------------------------------------------------------|\r\n\r\n</b><u>[Intro] <i>Dm</i>  <i>A</i>  <i>Dm</i>  <i>A</i>\r\n\r\n</u><u>       <i>Dm</i>\r\n</u><u>Se o Espírito de Deus se move em mim\r\n</u><u>   <i>A</i>                  <i>Dm</i>\r\n</u><u>Eu danço como o Rei Davi\r\n</u><u>       <i>Dm</i>\r\n</u><u>Se o Espírito de Deus se move em mim\r\n</u><u>   <i>A</i>                  <i>Dm</i>\r\n</u><u>Eu danço como o Rei Davi\r\n\r\n</u><u>   <i>Gm</i>        <i>Dm</i>\r\n</u><u>Eu danço, eu danço\r\n</u><u>   <i>A</i>                  <i>Dm</i>\r\n</u><u>Eu danço como o rei Davi\r\n</u><u>   <i>Gm</i>        <i>Dm</i>\r\n</u><u>Eu danço, eu danço\r\n</u><u>   <i>A</i>                  <i>Dm</i>\r\n</u><u>Eu danço como o rei Davi\r\n\r\n</u><u>       <i>Dm</i>\r\n</u><u>Se o Espírito de Deus se move em mim\r\n</u><u>   <i>A</i>                 <i>Dm</i>\r\n</u><u>Eu pulo como o Rei Davi\r\n</u><u>       <i>Dm</i>\r\n</u><u>Se o Espírito de Deus se move em mim\r\n</u><u>   <i>A</i>                 <i>Dm</i>\r\n</u><u>Eu pulo como o Rei Davi\r\n\r\n</u><u>   <i>Gm</i>       <i>Dm</i>\r\n</u><u>Eu pulo, eu pulo\r\n</u><u>   <i>A</i>                 <i>Dm</i>\r\n</u><u>Eu pulo como o rei Davi\r\n</u><u>   <i>Gm</i>       <i>Dm</i>\r\n</u><u>Eu pulo, eu pulo\r\n</u><u>   <i>A</i>                 <i>Dm</i>\r\n</u><u>Eu pulo como o rei Davi\r\n\r\n</u><u>       <i>Dm</i>\r\n</u><u>Se o Espírito de Deus se move em mim\r\n</u><u>   <i>A</i>                  <i>Dm</i>\r\n</u><u>Eu grito como o Rei Davi\r\n</u><u>       <i>Dm</i>\r\n</u><u>Se o Espírito de Deus se move em mim\r\n</u><u>   <i>A</i>                  <i>Dm</i>\r\n</u><u>Eu grito como o Rei Davi\r\n\r\n</u><u>   <i>Gm</i>        <i>Dm</i>\r\n</u><u>Eu grito, eu grito\r\n</u><u>   <i>A</i>                  <i>Dm</i>\r\n</u><u>Eu grito como o rei Davi\r\n</u><u>   <i>Gm</i>        <i>Dm</i>\r\n</u><u>Eu grito, eu grito\r\n</u><u>   <i>A</i>                  <i>Dm</i>\r\n</u><u>Eu grito como o rei Davi\r\n\r\n</u><u>(Riff 1)\r\n\r\n</u><u>       <i>D#m</i>\r\n</u><u>Se o Espírito de Deus se move em mim\r\n</u><u>   <i>A#</i>                 <i>D#m</i>\r\n</u><u>Eu danço como o Rei Davi\r\n</u><u>       <i>D#m</i>\r\n</u><u>Se o Espírito de Deus se move em mim\r\n</u><u>   <i>A#</i>                 <i>D#m</i>\r\n</u><u>Eu danço como o Rei Davi\r\n\r\n</u><u>   <i>G#m</i>       <i>D#m</i>\r\n</u><u>Eu danço, eu danço\r\n</u><u>   <i>A#</i>                 <i>D#m</i>\r\n</u><u>Eu danço como o rei Davi\r\n</u><u>   <i>G#m</i>       <i>D#m</i>\r\n</u><u>Eu danço, eu danço\r\n</u><u>   <i>A#</i>                 <i>D#m</i>\r\n</u><u>Eu danço como o rei Davi\r\n\r\n</u><u>       <i>D#m</i>\r\n</u><u>Se o Espírito de Deus se move em mim\r\n</u><u>   <i>A#</i>                <i>D#m</i>\r\n</u><u>Eu pulo como o Rei Davi\r\n</u><u>       <i>D#m</i>\r\n</u><u>Se o Espírito de Deus se move em mim\r\n</u><u>   <i>A#</i>                <i>D#m</i>\r\n</u><u>Eu pulo como o Rei Davi\r\n\r\n</u><u>   <i>G#m</i>      <i>D#m</i>\r\n</u><u>Eu pulo, eu pulo\r\n</u><u>   <i>A#</i>                <i>D#m</i>\r\n</u><u>Eu pulo como o rei Davi\r\n</u><u>   <i>G#m</i>      <i>D#m</i>\r\n</u><u>Eu pulo, eu pulo\r\n</u><u>   <i>A#</i>                <i>D#m</i>\r\n</u><u>Eu pulo como o rei Davi\r\n\r\n</u><u>       <i>D#m</i>\r\n</u><u>Se o Espírito de Deus se move em mim\r\n</u><u>   <i>A#</i>                 <i>D#m</i>\r\n</u><u>Eu grito como o Rei Davi\r\n</u><u>       <i>D#m</i>\r\n</u><u>Se o Espírito de Deus se move em mim\r\n</u><u>   <i>A#</i>                 <i>D#m</i>\r\n</u><u>Eu grito como o Rei Davi\r\n\r\n</u><u>   <i>G#m</i>       <i>D#m</i>\r\n</u><u>Eu grito, eu grito\r\n</u><u>   <i>A#</i>                 <i>D#m</i>\r\n</u><u>Eu grito como o rei Davi\r\n</u><u>   <i>G#m</i>       <i>D#m</i>\r\n</u><u>Eu grito, eu grito\r\n</u><u>   <i>A#</i>                 <i>D#m</i>\r\n</u><u>Eu grito como o rei Davi\r\n\r\n</u><u>   <i>G#m</i>       <i>D#m</i>\r\n</u><u>Eu danço, eu pulo\r\n</u><u>   <i>A#</i>                 <i>D#m</i>\r\n</u><u>Eu grito como o rei Davi\r\n</u><u>   <i>G#m</i>       <i>D#m</i>\r\n</u><u>Eu danço, eu pulo\r\n</u><u>   <i>A#</i>                 <i>D#m</i>\r\n</u><u>Eu grito como o rei Davi\r\n\r\n</u><u><i>Final</i> <i>D#m</i>  <i>A#</i>  <i>D#m</i></u>"
}