{
  "id": "anderson-freire-a-cruz-e-o-paraiso-47f15103f6",
  "title": "A Cruz e o Paraíso",
  "artist": "Anderson Freire",
  "collection": "cifras_multi",
  "fileType": "html",
  "key": "D",
  "updatedAt": "2026-04-23T21:39:59.005Z",
  "html": "<u>[Primeira Parte]\r\n\r\n</u><u>       <i>D</i>                             <i>Bm7</i>  <i>G</i>\r\n</u><u>Oh, Jesus, reconheço quem Tu és na cruz\r\n</u><u>       <i>D</i>                             <i>Bm7</i>  <i>G</i>\r\n</u><u>Oh, Jesus, reconheço quem Tu és na cruz\r\n\r\n</u><u><i>Bm7</i>                            <i>D</i>\r\n</u><u>  Ainda que eu não saiba tudo sobre Ti\r\n</u><u>       <i>A</i>              <i>Em7</i>\r\n</u><u>És Senhor de tudo em mim\r\n</u><u><i>Bm7</i>                            <i>D</i>\r\n</u><u>  Ainda que eu não saiba tudo sobre Ti\r\n</u><u>       <i>A</i>              <i>G</i>\r\n</u><u>És Senhor de tudo em mim\r\n\r\n</u><u>[Pré-Refrão]\r\n\r\n</u><u> <i>D</i>\r\n</u><u>Lembra-te de mim quando entrares no paraíso\r\n</u><u> <i>Bm7</i>                        <i>G</i>\r\n</u><u>Lembra-te de mim quando entrares no paraíso\r\n</u><u> <i>D</i>\r\n</u><u>Lembra-te de mim quando entrares no paraíso\r\n</u><u> <i>Bm7</i>                 <i>G</i>\r\n</u><u>Lembra-te de mim, Jesus\r\n\r\n</u><u>[Refrão]\r\n\r\n</u><u><i>D</i>         <i>A</i>               <i>Bm7</i>\r\n</u><u>  Eu me prostro aos Teus pés\r\n</u><u>        <i>G</i>\r\n</u><u>Eu me prostro\r\n</u><u><i>D</i>        <i>A</i>              <i>Bm7</i>\r\n</u><u>  Eu me rendo aos Teus pés\r\n</u><u>       <i>G</i>\r\n</u><u>Eu me rendo\r\n\r\n</u><u>[Segunda Parte]\r\n\r\n</u><u>       <i>D</i>                                <i>Bm7</i>  <i>G</i>\r\n</u><u>Filho meu, perdoei os teus pecados na cruz\r\n</u><u>       <i>D</i>                                <i>Bm7</i>  <i>G</i>\r\n</u><u>Filho meu, perdoei os teus pecados na cruz\r\n\r\n</u><u><i>Bm7</i>                      <i>D</i>\r\n</u><u>  Mesmo Eu sabendo tudo sobre ti\r\n</u><u>       <i>A</i>                <i>Em7</i>\r\n</u><u>Vem a mim que mudo teu fim\r\n</u><u><i>Bm7</i>                      <i>D</i>\r\n</u><u>  Mesmo Eu sabendo tudo sobre ti\r\n</u><u>       <i>A</i>                <i>G</i>\r\n</u><u>Vem a mim que mudo teu fim\r\n\r\n</u><u>[Pré-Refrão]\r\n\r\n</u><u> <i>D</i>\r\n</u><u>Passa pela cruz e entrarás no paraíso\r\n</u><u> <i>Bm7</i>                    <i>G</i>\r\n</u><u>Passa pela cruz e entrarás no paraíso\r\n</u><u> <i>D</i>\r\n</u><u>Passa pela cruz e entrarás no paraíso\r\n</u><u> <i>Bm7</i>              <i>G</i>\r\n</u><u>Passa pela cruz, filho\r\n\r\n</u><u>[Refrão]\r\n\r\n</u><u><i>D</i>         <i>A</i>               <i>Bm7</i>\r\n</u><u>  Eu me prostro aos Teus pés\r\n</u><u>        <i>G</i>\r\n</u><u>Eu me prostro\r\n</u><u><i>D</i>        <i>A</i>              <i>Bm7</i>\r\n</u><u>  Eu me rendo aos Teus pés\r\n</u><u>       <i>G</i>\r\n</u><u>Eu me rendo\r\n\r\n</u><u><i>D</i>         <i>A</i>               <i>Bm7</i>\r\n</u><u>  Eu me prostro aos Teus pés\r\n</u><u>        <i>G</i>\r\n</u><u>Eu me prostro\r\n</u><u><i>D</i>        <i>A</i>              <i>Bm7</i>\r\n</u><u>  Eu me rendo aos Teus pés\r\n</u><u>       <i>G</i>\r\n</u><u>Eu me rendo\r\n\r\n</u><u>[Ponte]\r\n\r\n</u><u><i>D</i>      <i>A</i>          <i>Bm7</i>    <i>G</i>\r\n</u><u>  Andaremos juntos, viveremos juntos\r\n</u><u><i>D</i>       <i>A</i>                <i>Bm7</i>         <i>G</i>\r\n</u><u>  Para sempre juntos no paraíso, no paraíso\r\n</u><u><i>D</i>      <i>Em7</i>        <i>D/F#</i>   <i>G</i>\r\n</u><u>  Andaremos juntos, viveremos juntos\r\n</u><u><i>D/A</i>     <i>Gm/Bb</i>            <i>Bm7</i>  <i>A</i>      <i>Em7</i>    <i>G</i>\r\n</u><u>  Para sempre juntos no paraíso, no paraíso\r\n\r\n</u><u>[Pré-Refrão]\r\n\r\n</u><u> <i>D</i>\r\n</u><u>Lembra-te de mim quando entrares no paraíso\r\n</u><u> <i>Bm7</i>                   <i>G</i>\r\n</u><u>Passa pela cruz e entrarás no paraíso\r\n</u><u> <i>D</i>\r\n</u><u>Lembra-te de mim quando entrares no paraíso\r\n</u><u> <i>Bm7</i>                   <i>G</i>\r\n</u><u>Passa pela cruz e entrarás no paraíso</u>"
}