{
  "id": "anderson-freire-promessa-46486aae3c",
  "title": "Promessa",
  "artist": "Anderson Freire",
  "collection": "cifras_multi",
  "fileType": "html",
  "key": "F",
  "updatedAt": "2026-04-23T21:46:58.092Z",
  "html": "<u>Intro: <i>F</i>  <i>Dm</i>  <i>G</i>  <i>C</i>  <i>E</i>\r\n\r\n</u><u><i>Am</i>          <i>E/G#</i>              <i>Am</i>        <i>G/B</i>\r\n</u><u>Vou voar em direção ao céu de cristo\r\n</u><u><i>C</i>        <i>G/B</i>                 <i>C</i>\r\n</u><u>Isto foi ele mesmo quem me prometeu\r\n</u><u><i>E</i>        <i>E/G#</i>                 <i>Am</i>\r\n</u><u>Vou voar pouco tempo aqui me resta\r\n</u><u><i>F</i>                     <i>C</i>\r\n</u><u>A minh'alma está com pressa\r\n</u><u><i>F</i>                     <i>E</i>        <i>E/G#</i>\r\n</u><u>Sim com pressa de no céu chegar\r\n\r\n</u><u><i>Am</i>           <i>E/G#</i>              <i>Am</i>\r\n</u><u>Vou voar em direção ao céu de gozo\r\n</u><u><i>G/B</i> <i>C</i>    <i>G/B</i>               <i>C</i>\r\n</u><u> Repouso para sempre ali eu terei\r\n</u><u><i>E</i>        <i>E/G#</i>                <i>Am</i>\r\n</u><u>Vou voar como voam os santos anjos\r\n</u><u><i>F</i>                <i>C</i>\r\n</u><u>Serafins também arcanjo\r\n</u><u> <i>F</i>                 <i>E</i>\r\n</u><u>Maravilhas ali desfrutarei\r\n\r\n</u><u> <i>A</i>                    <i>E</i>\r\n</u><u>Vou voar nas asas do vento\r\n</u><u>             <i>D</i>           <i>Bm</i>          <i>C#</i>\r\n</u><u>Na hora e no tempo em que Deus me chamar\r\n</u><u> <i>C</i>                         <i>G</i>\r\n</u><u>Vou voar quem dera fosse agora\r\n</u><u>               <i>F</i>          <i>Dm</i>        <i>E</i>    <i>E/G#</i>\r\n</u><u>Subir para a Glória onde meu Deus está\r\n</u><u>  <i>C</i>                         <i>G</i>\r\n</u><u>Vou voar quem dera fosse agora\r\n</u><u>               <i>F</i>                         <i>F</i>   <i>Dm</i>   <i>G</i>   <i>E/G#</i>\r\n</u><u>Subir para a Glória onde meu Deus está\r\n\r\n</u><u><i>Am</i>           <i>E/G#</i>              <i>Am</i>\r\n</u><u>Vou voar em direção ao céu de gozo\r\n</u><u><i>G/B</i> <i>C</i>    <i>G/B</i>               <i>C</i>\r\n</u><u> Repouso para sempre ali eu terei\r\n</u><u><i>E</i>        <i>E/G#</i>                <i>Am</i>\r\n</u><u>Vou voar como voam os santos anjos\r\n</u><u><i>F</i>                <i>C</i>\r\n</u><u>Serafins também arcanjo\r\n</u><u> <i>F</i>                 <i>E</i>\r\n</u><u>Maravilhas ali desfrutarei\r\n\r\n\r\n</u><u> <i>A</i>           <i>A</i> <i>G/B</i>    <i>B/C#</i>       <i>E</i>\r\n</u><u>Vou voar nas asas     do         vento\r\n</u><u>              <i>D</i>          <i>Bm</i>          <i>C#</i>\r\n</u><u>Na hora e no tempo em que Deus me chamar\r\n</u><u> <i>C</i>                         <i>G</i>\r\n</u><u>Vou voar quem dera fosse agora\r\n</u><u>               <i>F</i>              <i>Dm</i>         <i>E</i>    <i>E/G#</i>\r\n</u><u>Subir para a Glória onde meu Deus está\r\n</u><u> <i>C</i>                         <i>G</i>\r\n</u><u>Vou voar quem dera fosse agora\r\n</u><u>               <i>F</i>                         <i>F</i>   <i>G</i>   <i>Am</i>   <i>G/B</i>   <i>F</i>   <i>G</i>   <i>Am</i>   <i>G/B</i>\r\n</u><u>Subir para a Glória onde meu Deus está\r\n\r\n</u><u>  <i>C</i>           <i>G/B</i>         <i>F</i>   <i>Dm</i>    <i>E</i>\r\n</u><u>Vou voar a a a a    a a a a   a a a a\r\n</u><u>  <i>C</i>           <i>G/F</i>   <i>Dm</i>  <i>Am</i>\r\n</u><u>Vou voar a a a a</u>"
}