{
  "id": "anderson-freire-coracao-de-jo-e5f44611c1",
  "title": "Coração de jó",
  "artist": "Anderson Freire",
  "collection": "cifras_multi",
  "fileType": "html",
  "key": "D",
  "updatedAt": "2026-04-23T21:42:18.872Z",
  "html": "<u>Intro: <i>D</i>  <i>D9</i>  <i>D4</i>  <i>D</i>  <i>D9</i>  <i>D4</i>  <i>D</i>  <i>D9</i>  <i>D4</i>  <i>D</i>  <i>Em7</i>  <i>G</i>\r\n\r\n</u><u>Primeira Parte:\r\n</u><u> <i>D</i>   <i>Em7</i>                 <i>D/F#</i>\r\n</u><u>Deus olha pra dentro de mim\r\n</u><u> <i>G</i>            <i>A9</i>  <i>Bm7</i>\r\n</u><u>Recompõe meu coração\r\n</u><u>            <i>Em7</i>                     <i>A4</i>    <i>A</i>        <i>D</i>\r\n</u><u>Com a qualidade que fez de Jó um espelho para gerações\r\n\r\n</u><u>Segunda Parte:\r\n</u><u> <i>Em</i>                <i>D/F#</i>  <i>G</i>            <i>A9</i>   <i>Bm7</i>\r\n</u><u>Rico ou pobre ele foi    o que eu preciso ser\r\n</u><u>            <i>Em7</i>               <i>A4</i>           <i>A</i>\r\n</u><u>Coração sincero, homem reto pra não se perder\r\n\r\n</u><u>Pré-Refrão:\r\n</u><u>         <i>G</i>                      <i>Bm7</i>\r\n</u><u>Jó não blasfemou no dia em que tudo virou cinzas\r\n</u><u>       <i>Em7</i>        <i>G</i>                 <i>A4</i>\r\n</u><u>Eu preciso ser assim, Senhor, me ensina\r\n\r\n</u><u>Refrão:\r\n</u><u>         <i>D</i>            <i>A9</i>\r\n</u><u>Toca Senhor no meu caráter\r\n</u><u>         <i>Bm7</i>        <i>G</i>\r\n</u><u>Me dá o coração de Jó\r\n</u><u>             <i>D/F#</i>          <i>A/C#</i>\r\n</u><u>Que não blasfema, que te adora\r\n</u><u>          <i>Bm7</i>  <i>D</i>     <i>G</i>\r\n</u><u>Mesmo se tudo virar pó\r\n</u><u>          <i>D</i>             <i>A</i>\r\n</u><u>Toca, Senhor, no meu caráter\r\n</u><u>         <i>Bm7</i>        <i>G</i>\r\n</u><u>Me dá o coração de Jó\r\n</u><u>            <i>D/F#</i>             <i>A7</i>\r\n</u><u>Em meio ao tudo, em meio ao nada\r\n</u><u>         <i>Bm7</i> <i>F#m7</i>    <i>Em7</i>\r\n</u><u>Quero te adorar, Senhor\r\n</u><u>             <i>D</i>\r\n</u><u>Tu és meu melhor\r\n\r\n</u><u>( <i>D9</i>  <i>D4</i>  <i>D</i>  <i>G</i>  <i>Bm7</i>  <i>G/A</i> )\r\n\r\n</u><u>Segunda Parte:\r\n</u><u>    <i>Em</i>                <i>D/F#</i>  <i>G</i>            <i>A9</i>   <i>Bm7</i>\r\n</u><u>Jó rico ou pobre ele foi    o que eu preciso ser\r\n</u><u>            <i>Em7</i>               <i>A4</i>           <i>A</i>\r\n</u><u>Coração sincero, homem reto pra não se perder\r\n\r\n</u><u>Pré-Refrão:\r\n</u><u>         <i>G</i>                      <i>Bm7</i>\r\n</u><u>Jó não blasfemou no dia em que tudo virou cinzas\r\n</u><u>       <i>Em7</i>        <i>G</i>                 <i>A4</i>\r\n</u><u>Eu preciso ser assim, Senhor, me ensina\r\n\r\n</u><u>Refrão:\r\n</u><u>         <i>D</i>            <i>A9</i>\r\n</u><u>Toca Senhor no meu caráter\r\n</u><u>         <i>Bm7</i>        <i>G</i>\r\n</u><u>Me dá o coração de Jó\r\n</u><u>             <i>D/F#</i>          <i>A/C#</i>\r\n</u><u>Que não blasfema, que te adora\r\n</u><u>          <i>Bm7</i>  <i>D</i>     <i>G</i>\r\n</u><u>Mesmo se tudo virar pó\r\n</u><u>          <i>D</i>             <i>A</i>\r\n</u><u>Toca, Senhor, no meu caráter\r\n</u><u>         <i>Bm7</i>        <i>G</i>\r\n</u><u>Me dá o coração de Jó\r\n</u><u>            <i>D/F#</i>             <i>A7</i>\r\n</u><u>Em meio ao tudo, em meio ao nada\r\n</u><u>         <i>Bm7</i> <i>F#m7</i>    <i>Em7</i>\r\n</u><u>Quero te adorar, Senhor\r\n</u><u>             <i>D</i>\r\n</u><u>Tu és meu melhor\r\n\r\n</u><u>( <i>D9</i>  <i>D4</i>  <i>D</i>  <i>G</i>  <i>Bm7</i>  <i>G/A</i> )\r\n\r\n</u><u>         <i>D</i>            <i>A9</i>\r\n</u><u>Toca Senhor no meu caráter\r\n</u><u>         <i>Bm7</i>        <i>G</i>\r\n</u><u>Me dá o coração de Jó\r\n</u><u>             <i>D/F#</i>          <i>A/C#</i>\r\n</u><u>Que não blasfema, que te adora\r\n</u><u>          <i>Bm7</i>  <i>D</i>     <i>G</i>\r\n</u><u>Mesmo se tudo virar pó\r\n</u><u>          <i>D</i>             <i>A</i>\r\n</u><u>Toca, Senhor, no meu caráter\r\n</u><u>         <i>Bm7</i>        <i>G</i>\r\n</u><u>Me dá o coração de Jó\r\n</u><u>            <i>D/F#</i>             <i>A7</i>\r\n</u><u>Em meio ao tudo, em meio ao nada\r\n</u><u>         <i>Bm7</i> <i>F#m7</i>    <i>Em7</i>\r\n</u><u>Quero te adorar, Senhor\r\n</u><u>             <i>D</i>\r\n</u><u>Tu és meu melhor</u>"
}