{
  "id": "anderson-freire-amor-sem-preco-0d660b9a60",
  "title": "Amor sem preço",
  "artist": "Anderson Freire",
  "collection": "cifras_multi",
  "fileType": "html",
  "key": "A",
  "updatedAt": "2026-04-23T21:41:20.233Z",
  "html": "<u>INTRO: A9 (no violão, seria melhor uma dedilhada daí você mantém até a entrada da letra)\r\n\r\n\r\n</u><u><i>A9</i>                   <i>E9</i>\r\n</u><u>   Se agente quer colher tem que plantar\r\n</u><u><i>A9</i>                  <i>E9</i>\r\n</u><u>  Até mesmo para sorrir e para chorar\r\n</u><u><i>E7</i>                        <i>A9</i>        <i>G#m</i>\r\n</u><u>   Pra viver um grande amor tem que deixar\r\n</u><u><i>F#m</i>                       <i>B9</i>    <i>A9</i>   <i>E9</i>\r\n</u><u>De lado os sonhos que não cabem no peito\r\n\r\n\r\n</u><u>\"non non non\" (mantém em ' A9 ' e ' E ' de preferência em ' <i>E9</i> ')\r\n\r\n\r\n</u><u><i>A9</i>                   <i>E9</i>\r\n</u><u>  O meu lucro é perder pra te ganhar\r\n</u><u><i>A9</i>                   <i>E</i>\r\n</u><u>    Não foi hora pra poder te encontrar\r\n</u><u><i>E7</i>                        <i>A9</i>   <i>E9</i>\r\n</u><u>   Você é como uma dádiva do céu\r\n</u><u><i>Bb</i>             <i>A</i>           <i>E</i>\r\n</u><u>Jóia lapidada pelas mãos de Deus\r\n\r\n\r\n</u><u><i>E9</i>                    <i>A9</i>\r\n</u><u> Pra ganhar tem que ceder\r\n</u><u><i>B9</i>             <i>E9</i>\r\n</u><u>Não quero te perder\r\n</u><u>                  <i>A9</i>\r\n</u><u>Abro mão dos sonhos meus\r\n</u><u><i>B9</i>             <i>C9</i>\r\n</u><u>Pra ficar com você\r\n</u><u>  <i>G#m</i>           <i>A9</i>\r\n</u><u>Não vou me arrepender\r\n</u><u>  <i>E</i>               <i>F#m</i>\r\n</u><u>Estou plantando pra colher\r\n</u><u><i>A9</i>        <i>B9</i>      <i>E9</i>\r\n</u><u>Um amor sem preço                    (Repete 2x)\r\n\r\n</u><u>(REPETE A PARTIR DA 2ª ESTROFE)\r\n\r\n</u><u>Obrigado! &gt;</u>"
}