{
  "id": "anderson-freire-minha-casa-b64f374b56",
  "title": "Minha Casa",
  "artist": "Anderson Freire",
  "collection": "cifras_multi",
  "fileType": "html",
  "key": "G",
  "updatedAt": "2026-04-23T21:45:55.247Z",
  "html": "<u>[Intro] <i>G/D</i>  <i>C/D</i>\r\n\r\n</u><u><i>G</i>                               <i>Em</i>\r\n</u><u>Eu rejeito tudo o que não vem de ti\r\n</u><u>                                   <i>C</i>\r\n</u><u>Minha família é separada para te servir\r\n</u><u>         <i>G/B</i>               <i>Am</i>\r\n</u><u>Sobre ela está a tua forte mão\r\n</u><u>                                   <i>D</i>\r\n</u><u>Protegendo os sonhos dos nossos corações\r\n</u><u><i>G</i>                                        <i>Em</i>\r\n</u><u>Eu profetizo sobre a minha casa água e pão\r\n</u><u>                                  <i>C</i>\r\n</u><u>Saúde para os meus filhos, santificação\r\n</u><u>  <i>G/B</i>                   <i>Am</i>\r\n</u><u>Tua palavra para nos manter\r\n</u><u>                               <i>D</i>\r\n</u><u>Firmes sobre a rocha que nunca irá ceder\r\n\r\n</u><u><i>G</i>                            <i>Em</i>\r\n</u><u>Minha casa, edificada em ti está\r\n</u><u>                                      <i>C</i>\r\n</u><u>Minha família, foi consagrada pra te adorar\r\n</u><u>            <i>G/B</i>\r\n</u><u>Minhas primícias\r\n</u><u>              <i>Am</i>\r\n</u><u>Eu sempre quero te entregar\r\n</u><u>                                <i>D</i>\r\n</u><u>E tuas bênçãos irão sempre me acompanhar\r\n\r\n</u><u><i>G</i>                                 <i>Em</i>\r\n</u><u>Os teus planos são os nossos e não há\r\n\r\n</u><u>Em qualquer parte do mundo\r\n</u><u>                <i>C</i>\r\n</u><u>Ou em qualquer lugar\r\n</u><u>       <i>G/B</i>                    <i>Am</i>\r\n</u><u>Outro bem maior que se compare a ti\r\n</u><u>                              <i>D</i>\r\n</u><u>Nossa adoração se rende só a ti\r\n\r\n</u><u> <i>G</i>                                  <i>Em</i>\r\n</u><u>A tempestade está batendo em nossa porta\r\n</u><u>                                     <i>C</i>\r\n</u><u>Pra fazer na minha casa vítimas de morte\r\n</u><u>      <i>G/B</i>                       <i>Am</i>\r\n</u><u>Mas eu não aceito em nome de Jesus\r\n</u><u>                                 <i>D</i>\r\n</u><u>Minha família mora debaixo de tua luz</u>"
}