{
  "id": "isadora-pompeo-desperta-a941157a56",
  "title": "Desperta",
  "artist": "Isadora Pompeo",
  "collection": "cifras_multi",
  "fileType": "html",
  "key": "C",
  "updatedAt": "2026-04-21T11:45:32.445Z",
  "html": "<u>[Intro] <i>C</i>  <i>G</i>  <i>F</i>  <i>G</i>\r\n\r\n</u><u>    <i>C</i>\r\n</u><u>Liberta a tua igreja\r\n</u><u>        <i>G</i>\r\n</u><u>Desperta tua noiva\r\n</u><u>      <i>Dm</i>\r\n</u><u>Troca as nossas vestes\r\n</u><u>     <i>G</i>\r\n</u><u>Ensine a orar\r\n</u><u>         <i>Am</i>\r\n</u><u>Nos traga pra perto\r\n</u><u>         <i>G</i>\r\n</u><u>Abra os nossos olhos\r\n</u><u>        <i>Dm</i>\r\n</u><u>Queremos ser livres\r\n</u><u>    <i>G</i>\r\n</u><u>Ensine a amar\r\n\r\n</u><u> <i>C</i>\r\n</u><u>Aquele que não chora\r\n</u><u>pela dor do seu irmão\r\n</u><u>   <i>G</i>\r\n</u><u>Que não se compadece\r\n</u><u>de um fraco coração\r\n</u><u>  <i>Dm</i>\r\n</u><u>Que Deus está servindo?\r\n</u><u>Porque canta és bem vindo\r\n</u><u>        <i>F</i>  <i>G</i>\r\n</u><u>Se despreza o amor\r\n</u><u><i>C</i>\r\n</u><u>Preste atenção na ferida que formou\r\n</u><u><i>G</i>\r\n</u><u>E quem pode curar com palavras de amor\r\n</u><u>     <i>Dm</i>\r\n</u><u>Se o ego não entende, julgamento não permite\r\n</u><u>              <i>G</i>\r\n</u><u>Que corpo é esse que tu mora?\r\n</u><u>           <i>C</i>\r\n</u><u>Liberta a tua igreja\r\n</u><u>        <i>G</i>\r\n</u><u>Desperta tua noiva\r\n</u><u>              <i>Dm</i>\r\n</u><u>Troca as nossas vestes\r\n</u><u>         <i>G</i>\r\n</u><u>Ensine a orar\r\n</u><u>          <i>Am</i>\r\n</u><u>Nos traga pra perto\r\n</u><u>        <i>G</i>\r\n</u><u>Abra os nossos olhos\r\n</u><u>        <i>Dm</i>\r\n</u><u>Queremos ser livres\r\n</u><u>          <i>G</i>\r\n</u><u>Ensine a amar\r\n</u><u><i>C</i>\r\n</u><u>Pai estou chorando pela igreja\r\n</u><u><i>G</i>\r\n</u><u>Pai choramos pela noiva\r\n</u><u><i>Dm</i>             <i>G</i>\r\n</u><u>Pai nos coloque em comunhão\r\n</u><u><i>Am</i>\r\n</u><u>Pai estou chorando pela igreja\r\n</u><u><i>G</i>\r\n</u><u>Pai choramos pela noiva\r\n</u><u><i>Dm</i>              <i>G</i>\r\n</u><u>Pai nos coloque em comunhão\r\n</u><u><i>C</i>\r\n</u><u>Liberta a tua igreja\r\n</u><u><i>G</i>\r\n</u><u>Desperta tua noiva\r\n</u><u><i>Dm</i>\r\n</u><u>Troca as nossas vestes\r\n</u><u>         <i>G</i>\r\n</u><u>Ensine a orar\r\n</u><u>         <i>Am</i>\r\n</u><u>Nos traga pra perto\r\n</u><u>       <i>G</i>\r\n</u><u>Abra os nossos olhos\r\n</u><u>        <i>Dm</i>\r\n</u><u>Queremos ser livres\r\n</u><u>         <i>G</i>\r\n</u><u>Ensine a amar\r\n</u><u><i>C</i>\r\n</u><u>Liberta a tua igreja\r\n</u><u><i>G</i>\r\n</u><u>Desperta tua noiva\r\n</u><u><i>Dm</i>\r\n</u><u>Troca as nossas vestes\r\n</u><u>   <i>G</i>\r\n</u><u>Ensine a orar\r\n</u><u><i>Am</i>\r\n</u><u>Nos traga pra perto\r\n</u><u><i>G</i>\r\n</u><u>Abra os nossos olhos\r\n</u><u><i>Dm</i>\r\n</u><u>Queremos ser livres\r\n</u><u>  <i>F</i>    <i>G</i>\r\n</u><u>Ensine a amar</u>"
}