{
  "id": "luma-elpidio-quem-es-pra-mim-5e1d976e0d",
  "title": "Quem és pra mim",
  "artist": "Luma Elpidio",
  "collection": "cifras_multi",
  "fileType": "html",
  "key": "A",
  "updatedAt": "2026-04-21T12:15:39.183Z",
  "html": "<u>[Intro] <i>Am7</i>  <i>F9</i>  <i>C</i>\r\n</u><u>        <i>Am7</i>  <i>F9</i>  <i>C</i>\r\n\r\n</u><u>[Primeira Parte]\r\n\r\n</u><u><i>Am7</i>                 <i>F9</i>\r\n</u><u>   Me humilho aos teus pés\r\n</u><u>                  <i>C</i>         <i>G/B</i>\r\n</u><u>Pra te dizer quem És pra mim\r\n</u><u><i>Am7</i>                <i>F9</i>\r\n</u><u>   Me humilho aos Teus pés\r\n</u><u>                  <i>C</i>         <i>G/B</i>\r\n</u><u>Pra te dizer quem És pra mim\r\n\r\n</u><u>[Pré-Refrão]\r\n\r\n</u><u>            <i>Am7</i>\r\n</u><u>Pois Tu és tudo que eu preciso\r\n</u><u>       <i>F9</i>                       <i>C</i>      <i>G/B</i>\r\n</u><u>Meu socorro meu auxílio, meu libertador\r\n</u><u>            <i>Am7</i>\r\n</u><u>Pois Tu És mais que um amigo\r\n</u><u>       <i>F9</i>                   <i>C</i>          <i>G/B</i>\r\n</u><u>Meu refúgio meu abrigo, és meu salvador\r\n\r\n</u><u>( <i>Am7</i>  <i>F9</i>  <i>C</i> )\r\n</u><u>( <i>Am7</i>  <i>F9</i>  <i>C</i> )\r\n\r\n</u><u>[Primeira Parte]\r\n\r\n</u><u><i>Am7</i>                 <i>F9</i>\r\n</u><u>   Me humilho aos teus pés\r\n</u><u>                  <i>C</i>         <i>G/B</i>\r\n</u><u>Pra te dizer quem És pra mim\r\n</u><u><i>Am7</i>                <i>F9</i>\r\n</u><u>   Me humilho aos Teus pés\r\n</u><u>                  <i>C</i>         <i>G/B</i>\r\n</u><u>Pra te dizer quem És pra mim\r\n\r\n</u><u>[Pré-Refrão]\r\n\r\n</u><u>            <i>Am7</i>\r\n</u><u>Pois Tu és tudo que eu preciso\r\n</u><u>       <i>F9</i>                       <i>C</i>      <i>G/B</i>\r\n</u><u>Meu socorro meu auxílio, meu libertador\r\n</u><u>            <i>Am7</i>\r\n</u><u>Pois Tu És mais que um amigo\r\n</u><u>       <i>F9</i>                   <i>C</i>          <i>G/B</i>\r\n</u><u>Meu refúgio meu abrigo, és meu salvador\r\n\r\n</u><u>            <i>Am7</i>\r\n</u><u>Pois Tu és tudo que eu preciso\r\n</u><u>       <i>F9</i>                       <i>C</i>      <i>G/B</i>\r\n</u><u>Meu socorro meu auxílio, meu libertador\r\n</u><u>            <i>Am7</i>\r\n</u><u>Pois Tu És mais que um amigo\r\n</u><u>       <i>F9</i>                   <i>C</i>          <i>G/B</i>\r\n</u><u>Meu refúgio meu abrigo, és meu salvador\r\n\r\n</u><u>[Refrão]\r\n\r\n</u><u>            <i>Am7</i>                 <i>Dm7</i>\r\n</u><u>E não há palavras pra te descrever\r\n</u><u>                <i>C</i>                    <i>G/B</i>\r\n</u><u>Meu coração se cala por não compreender\r\n</u><u>              <i>Am7</i>                <i>Dm7</i>\r\n</u><u>E eu entrego tudo pra não te perder\r\n</u><u>                  <i>C</i>\r\n</u><u>Pois nada vale o mundo\r\n</u><u>               <i>G/B</i>\r\n</u><u>Se eu te conhecer\r\n\r\n</u><u>[Pré-Refrão]\r\n\r\n</u><u>            <i>Am7</i>\r\n</u><u>Pois Tu és tudo que eu preciso\r\n</u><u>       <i>F9</i>                       <i>C</i>      <i>G/B</i>\r\n</u><u>Meu socorro meu auxílio, meu libertador\r\n</u><u>            <i>Am7</i>\r\n</u><u>Pois Tu És mais que um amigo\r\n</u><u>       <i>F9</i>                   <i>C</i>          <i>G/B</i>\r\n</u><u>Meu refúgio meu abrigo, és meu salvador\r\n\r\n</u><u>[Refrão]\r\n\r\n</u><u>            <i>Am7</i>                 <i>F9</i>\r\n</u><u>E não há palavras pra te descrever\r\n</u><u>                <i>C</i>                    <i>G/B</i>\r\n</u><u>Meu coração se cala por não compreender\r\n</u><u>              <i>Am7</i>                <i>F9</i>\r\n</u><u>E eu entrego tudo pra não te perder\r\n</u><u>                  <i>C</i>\r\n</u><u>Pois nada vale o mundo\r\n</u><u>               <i>G/B</i>\r\n</u><u>Se eu te conhecer\r\n\r\n</u><u>[Segunda Parte]\r\n\r\n</u><u>                   <i>Am7</i>                <i>F9</i>\r\n</u><u>Quando eu te conheci tudo a minha volta\r\n</u><u>          <i>C</i>                       <i>G/B</i>\r\n</u><u>Perdeu o seu valor, tudo perde o seu valor\r\n</u><u>                  <i>Am7</i>                 <i>F9</i>\r\n</u><u>Não se compara a ti nada a minha volta\r\n</u><u>                  <i>C</i>                            <i>G/B</i>\r\n</u><u>Não se compara a ti,Senhor, não se compara ao teu amor\r\n\r\n</u><u>                   <i>Am7</i>                <i>F9</i>\r\n</u><u>Quando eu te conheci tudo a minha volta\r\n</u><u>          <i>C</i>                       <i>G/B</i>\r\n</u><u>Perdeu o seu valor, tudo perde o seu valor\r\n</u><u>                  <i>Am7</i>                 <i>F9</i>\r\n</u><u>Não se compara a ti nada a minha volta\r\n</u><u>                  <i>C</i>                            <i>G/B</i>\r\n</u><u>Não se compara a ti,Senhor, não se compara ao teu amor\r\n\r\n</u><u>[Ponte]\r\n\r\n</u><u><i>Am7</i>\r\n</u><u>   E tudo perde o seu valor\r\n</u><u>                       <i>F9</i>\r\n</u><u>Se comparado ao Teu amor, Senhor\r\n</u><u><i>C</i>\r\n</u><u> E tudo perde o seu valor\r\n</u><u>                      <i>G/B</i>\r\n</u><u>Se comparado ao Teu amor\r\n\r\n</u><u><i>Am7</i>\r\n</u><u>   E tudo perde o seu valor\r\n</u><u>                       <i>F9</i>\r\n</u><u>Se comparado ao Teu amor, Senhor\r\n</u><u><i>C</i>\r\n</u><u> E tudo perde o seu valor\r\n</u><u>                      <i>G/B</i>\r\n</u><u>Se comparado ao Teu amor\r\n\r\n</u><u><i>Am7</i>\r\n</u><u>   E tudo perde o seu valor\r\n</u><u>                       <i>F9</i>\r\n</u><u>Se comparado ao Teu amor, Senhor\r\n</u><u><i>C</i>\r\n</u><u> E tudo perde o seu valor\r\n</u><u>                      <i>G/B</i>\r\n</u><u>Se comparado ao Teu amor\r\n\r\n</u><u><i>Am7</i>\r\n</u><u>   E tudo perde o seu valor\r\n</u><u>                       <i>F9</i>\r\n</u><u>Se comparado ao Teu amor, Senhor\r\n</u><u><i>C</i>\r\n</u><u> E tudo perde o seu valor\r\n</u><u>                      <i>G/B</i>\r\n</u><u>Se comparado ao Teu amor\r\n\r\n</u><u>[Refrão]\r\n\r\n</u><u>            <i>Am7</i>                 <i>F9</i>\r\n</u><u>E não há palavras pra te descrever\r\n</u><u>                <i>C</i>                    <i>G/B</i>\r\n</u><u>Meu coração se cala por não compreender\r\n</u><u>              <i>Am7</i>                <i>F9</i>\r\n</u><u>E eu entrego tudo pra não te perder\r\n</u><u>                  <i>C</i>\r\n</u><u>Pois nada vale o mundo\r\n</u><u>               <i>G/B</i>\r\n</u><u>Se eu te conhecer\r\n</u><u>   <i>Am7</i>\r\n</u><u>Jesus</u>"
}