{
  "id": "luma-elpidio-leva-me-alem-part-bruna-branco-fbda5df332",
  "title": "Leva-me Além (part. Bruna Branco)",
  "artist": "Luma Elpidio",
  "collection": "cifras_multi",
  "fileType": "html",
  "key": "E",
  "updatedAt": "2026-04-21T12:17:16.942Z",
  "html": "<u><i>Em</i>    <i>C7M</i>   <i>Em</i>    <i>C7M</i>\r\n</u><u>Ooooo ooooo ooooo ooooo\r\n\r\n</u><u> <i>Em</i>             <i>C7M</i>\r\n</u><u>Superficialmente não dá mais\r\n</u><u><i>Em</i>              <i>C7M</i>\r\n</u><u>O possivelmente não dá mais\r\n</u><u><i>Em</i>              <i>C7M</i>\r\n</u><u>Inconstantemente não dá mais\r\n</u><u><i>Em</i>             <i>C7M</i>\r\n</u><u>O indiferente não dá mais\r\n\r\n</u><u><i>Em</i>    <i>C7M</i>    <i>Em</i>    <i>C7M</i>\r\n</u><u>Ooooo ooooo ooooo ooooo\r\n\r\n</u><u> <i>Em</i>      <i>C7M</i>  <i>Em</i>          <i>D6</i>\r\n</u><u>Leva-me além do que posso ver\r\n</u><u><i>Em</i>             <i>C7M</i>           <i>G</i>       <i>D6</i>\r\n</u><u>Quero ir mais fundo em Ti Te conhecer\r\n</u><u><i>Em</i>        <i>C7M</i>  <i>Em</i>          <i>D6</i>\r\n</u><u>Leva-me além do que já provei\r\n</u><u><i>Em</i>            <i>C7M</i>             <i>G</i>         <i>D6</i>\r\n</u><u>Pois ainda há muito em Ti que eu não sei\r\n\r\n</u><u><i>Em</i>                       <i>C7M</i>                 <i>Em</i>             <i>C7M</i>\r\n</u><u>As coisas que antes me prendiam me mantinham ali, tão longe de Ti\r\n</u><u><i>Em</i>                     <i>C7M</i>                      <i>Dbm7(5-)</i>\r\n</u><u>Hoje já não me prendem mais, foram deixadas para traz, você levou\r\n</u><u> <i>C7M</i>\r\n</u><u>Sobre si\r\n\r\n</u><u><i>Final</i> <i>Em</i>  <i>Dbm7(5-)</i>  <i>C7M</i>  <i>A4</i>\r\n</u><u>        <i>Em</i>  <i>Dbm7(5-)</i>  <i>C7M</i>  <i>D6</i></u>"
}