{
  "id": "mateus-brito-glorioso-dia-acdcaa23ef",
  "title": "Glorioso Dia",
  "artist": "Mateus Brito",
  "collection": "cifras_multi",
  "fileType": "html",
  "key": "D",
  "updatedAt": "2026-04-21T11:58:57.872Z",
  "html": "<u>   <i>D9</i>\r\n</u><u>Minha vergonha me sepultou\r\n</u><u>       <i>Bm9</i>\r\n</u><u>Eu buscava um salvador\r\n</u><u>            <i>G9</i>\r\n</u><u>Mas Teu perdão\r\n</u><u>         <i>D9</i>\r\n</u><u>Me libertou\r\n\r\n</u><u>         <i>D9</i>\r\n</u><u>Morto estava em meu interior\r\n</u><u>         <i>Bm9</i>\r\n</u><u>Me escondia de Ti, Senhor\r\n</u><u>            <i>G9</i>\r\n</u><u>Mas Teu perdão\r\n</u><u>         <i>D9</i>\r\n</u><u>Me libertou\r\n\r\n</u><u>           <i>G</i>\r\n</u><u>Tu me chamaste\r\n</u><u>                <i>D</i>\r\n</u><u>E eu voltei a viver\r\n</u><u>          <i>G</i>\r\n</u><u>Glorioso dia\r\n</u><u>                    <i>D</i>\r\n</u><u>Teu sangue me salvou\r\n\r\n</u><u>          <i>G</i>\r\n</u><u>Tu me chamaste\r\n</u><u>                <i>Bm</i>\r\n</u><u>E eu voltei a viver\r\n</u><u>          <i>G</i>\r\n</u><u>Glorioso dia\r\n</u><u>                  <i>D</i>\r\n</u><u>Teu sangue me salvou\r\n\r\n</u><u>         <i>D9</i>\r\n</u><u>Por Tua graça eu salvo sou\r\n</u><u>            <i>Bm9</i>\r\n</u><u>Teu grande amor me libertou\r\n</u><u>         <i>G</i>\r\n</u><u>Eu renasci\r\n\r\n</u><u>              <i>D</i>\r\n</u><u>Quando te conheci\r\n\r\n</u><u>      <i>G</i>\r\n</u><u>Tu me chamaste\r\n</u><u>                <i>D</i>\r\n</u><u>E eu voltei a viver\r\n</u><u>          <i>G</i>\r\n</u><u>Glorioso dia\r\n</u><u>                  <i>D</i>\r\n</u><u>Teu sangue me resgatou\r\n</u><u>          <i>G</i>\r\n</u><u>Tu me chamaste\r\n</u><u>                <i>Bm</i>\r\n</u><u>E eu voltei a viver\r\n\r\n</u><u>          <i>G</i>\r\n</u><u>Glorioso dia\r\n</u><u>                  <i>D</i>\r\n</u><u>Teu sangue me salvou\r\n\r\n</u><u>  <i>D</i>\r\n</u><u>Do meu pecado, me resgataste\r\n\r\n</u><u>Em Tua glória, cadeias se rompem\r\n</u><u>  <i>D</i>\r\n</u><u>Sozinho estava e sem consolo\r\n\r\n</u><u>Agora sou um cidadão do Céu\r\n\r\n</u><u><i>D</i>\r\n</u><u>Do meu pecado, me resgataste\r\n</u><u>         <i>D</i>\r\n</u><u>Em Tua glória, cadeias se rompem\r\n</u><u><i>D</i>\r\n</u><u>Sozinho estava e sem consolo\r\n</u><u>  <i>D</i>\r\n</u><u>Agora sou um cidadão do Céu\r\n\r\n</u><u><i>D</i>\r\n</u><u>Ferido estava e me curaste\r\n</u><u> <i>D</i>\r\n</u><u>Teu amor é o ar que eu respiro\r\n</u><u> <i>Bm</i>           <i>A</i>        <i>A9</i>\r\n</u><u>Tenho futuro e agora vejo\r\n</u><u>                  <i>G</i>\r\n</u><u>Porque Tu me chamaste\r\n</u><u>                <i>D</i>\r\n</u><u>E eu voltei a viver\r\n\r\n</u><u>          <i>G</i>\r\n</u><u>Glorioso dia\r\n</u><u>                  <i>D</i>\r\n</u><u>Teu sangue me resgatou\r\n</u><u>      <i>G</i>\r\n</u><u>Tu me chamaste\r\n</u><u>                <i>Bm</i>\r\n</u><u>E eu voltei a viver\r\n</u><u>          <i>G</i>\r\n</u><u>Glorioso dia\r\n</u><u>                  <i>D</i>\r\n</u><u>Teu sangue me salvou</u>"
}