{
  "id": "midian-lima-a-bencao-do-senhor-7dfc438ae7",
  "title": "A Bênção do Senhor",
  "artist": "Midian Lima",
  "collection": "cifras_multi",
  "fileType": "html",
  "key": "C",
  "updatedAt": "2026-04-23T21:35:59.198Z",
  "html": "<u>[Intro] <i>C</i>  <i>Am</i>\r\n</u><u>        <i>D</i>  <i>A</i>  <i>Bm</i>\r\n\r\n</u><u>     <i>A</i>\r\n</u><u>Meu amor\r\n</u><u>                         <i>F#m</i>\r\n</u><u>Hoje é um dia muito especial\r\n</u><u>                  <i>E</i>                      <i>D</i>\r\n</u><u>Me lembro aquele dia em que eu estava tão mal\r\n</u><u>         <i>C#m</i>\r\n</u><u>Você chegou, me deu carinho\r\n</u><u>    <i>Bm</i>           <i>E</i>\r\n</u><u>Mudou o meu destino\r\n</u><u>    <i>A</i>\r\n</u><u>Meu amor\r\n</u><u>                                  <i>F#m</i>\r\n</u><u>Naquele dia começou uma linda história\r\n</u><u>          <i>E</i>              <i>D</i>\r\n</u><u>Algo que marcará nossa memória\r\n</u><u>                                    <i>F#m</i>\r\n</u><u>Nossos filhos e os filhos dos nossos filhos\r\n</u><u>     <i>B</i>\r\n</u><u>Todos saberão\r\n</u><u>       <i>E</i>            <i>F#m</i>             <i>E</i>         <i>A</i>\r\n</u><u>Eu te amo E eu vou gritar pro mundo inteiro ouvir\r\n</u><u>                           <i>F#m</i>\r\n</u><u>Que o nosso amor não tem limites\r\n</u><u>                             <i>A</i>\r\n</u><u>Até o último momento irei te amar\r\n</u><u>                                  <i>E</i>\r\n</u><u>A bênção do Senhor está no nosso lar\r\n</u><u>                                      <i>A</i>\r\n</u><u>Te amo e vou gritar pro mundo inteiro ouvir\r\n</u><u>             <i>E/G#</i>           <i>F#m</i>\r\n</u><u>Que o nosso amor não tem limites\r\n</u><u>                            <i>A</i>\r\n</u><u>Até o último momento irei te amar\r\n</u><u>                                 <i>F#m</i>\r\n</u><u>A bênção do Senhor está no nosso lar\r\n\r\n</u><u>( <i>C#m</i>  <i>D7</i>  <i>F#m7</i>  <i>C#m</i>  <i>D</i> )\r\n\r\n</u><u>    <i>A</i>\r\n</u><u>Meu amor\r\n</u><u>                         <i>D</i>\r\n</u><u>Hoje é um dia muito especial\r\n</u><u>                                        <i>F#m</i>\r\n</u><u>Me lembro aquele dia em que eu estava tão mal\r\n</u><u>             <i>E</i>\r\n</u><u>Você chegou, me deu carinho\r\n</u><u>          <i>D</i>\r\n</u><u>Mudou o meu destino\r\n</u><u>    <i>A</i>\r\n</u><u>Meu amor\r\n</u><u>                           <i>E</i>       <i>D</i>\r\n</u><u>Naquele dia começou uma linda história\r\n</u><u>                          <i>F#m</i>\r\n</u><u>Algo que marcará nossa memória\r\n</u><u>                <i>E</i>                  <i>D</i>\r\n</u><u>Nossos filhos e os filhos dos nossos filhos\r\n</u><u>        <i>B</i>\r\n</u><u>Todos saberão\r\n</u><u>     <i>E</i>                                      <i>A</i>\r\n</u><u>Eu te amo E eu vou gritar pro mundo inteiro ouvir\r\n</u><u>                       <i>E/G#</i>  <i>F#m</i>\r\n</u><u>Que o nosso amor não tem limites\r\n</u><u>                              <i>A</i>\r\n</u><u>Até o último momento irei te amar\r\n</u><u>                  <i>F#m</i>       <i>B</i>      <i>E</i>\r\n</u><u>A bênção do Senhor está no nosso lar\r\n</u><u><i>E</i>                                      <i>A</i>\r\n</u><u>Te amo e vou gritar pro mundo inteiro ouvir\r\n</u><u>                       <i>G#º</i>  <i>F#m</i>\r\n</u><u>Que o nosso amor não tem limites\r\n</u><u>                              <i>A</i>\r\n</u><u>Até o último momento irei te amar\r\n</u><u>                  <i>F#m</i>       <i>B</i>      <i>E</i>\r\n</u><u>A bênção do Senhor está no nosso lar\r\n</u><u>       <i>F#m</i>                        <i>E</i>      <i>A</i>\r\n</u><u>Nosso Deus abençoou o nosso amor, nossa união\r\n</u><u>                        <i>B</i>    <i>C#m</i>\r\n</u><u>Porque tudo foi gerado em oração\r\n</u><u>                           <i>B</i>\r\n</u><u>E nada nem ninguém poderá destruir esse amor\r\n</u><u><i>F#m</i>                                <i>E</i>     <i>F#m</i>\r\n</u><u>Nosso Deus abençoou o nosso amor, nossa união\r\n</u><u>                        <i>B</i>    <i>C#m</i>\r\n</u><u>Porque tudo foi gerado em oração\r\n</u><u>                                      <i>B</i>\r\n</u><u>E nada nem ninguém poderá destruir nosso amor\r\n</u><u>   <i>Bb</i>   <i>C</i>\r\n</u><u>Nosso amor\r\n</u><u>            <i>F</i>      <i>Gm</i>             <i>F</i>        <i>Bb</i>\r\n</u><u>Eu te amo E eu vou gritar pro mundo inteiro ouvir\r\n</u><u>                             <i>Gm</i>\r\n</u><u>Que o nosso amor não tem limites\r\n</u><u>                         <i>F</i>    <i>Bb</i>\r\n</u><u>Até o último momento irei te amar\r\n</u><u>                            <i>C</i>     <i>F</i>\r\n</u><u>A bênção do Senhor está no nosso lar\r\n</u><u>    <i>F</i>                                   <i>Bb</i>\r\n</u><u>Te amo e vou gritar pro mundo inteiro ouvir\r\n</u><u>                       <i>F/A</i>   <i>Gm</i>\r\n</u><u>Que o nosso amor não tem limites\r\n</u><u>                        <i>F</i>     <i>Bb</i>\r\n</u><u>Até o último momento irei te amar\r\n</u><u>                                 <i>Dm</i>  <i>F/A</i>  <i>Gm</i>\r\n</u><u>A bênção do Senhor está no nosso lar\r\n</u><u>   <i>C</i> <i>A</i>            <i>Dm</i>  <i>Am</i>  <i>Gm</i>  <i>F</i>\r\n</u><u>Está no nosso lar</u>"
}