{
  "id": "ministerio-zoe-quando-a-luz-se-apagar-904eb26a13",
  "title": "Quando a luz se apagar",
  "artist": "Ministerio Zoe",
  "collection": "cifras_multi",
  "fileType": "html",
  "key": "E",
  "updatedAt": "2026-04-21T12:48:47.815Z",
  "html": "<u>[Intro] <i>Em</i>  <i>D</i>  <i>Am</i>  <i>Bm</i>\r\n\r\n</u><u><i>Em</i>                    <i>D</i>                   <i>C</i>\r\n</u><u>Um fogo queima em mim, clamo por mais de ti\r\n</u><u>                <i>D</i>                   <i>Em</i>\r\n</u><u>Eu quero muito mais, eu,preciso ir além\r\n</u><u>                          <i>D</i>                   <i>C</i>\r\n</u><u>Estou a procura de algo novo, preciso de um renovo\r\n</u><u>                   <i>Am</i>           <i>Em</i>\r\n</u><u>Meu coração quer mais, mais de ti\r\n\r\n</u><u>                <i>D</i>\r\n</u><u>Eu cansei de ser o mesmo\r\n</u><u>                 <i>C</i>\r\n</u><u>Eu cansei de ser eu mesmo\r\n</u><u>            <i>Am</i>\r\n</u><u>Eu quero tua vida em mim\r\n</u><u><i>Em</i>\r\n</u><u>Eu Jesus,Jesus e eu\r\n</u><u><i>D</i>\r\n</u><u>Eu sou teu,o Senhor  é meu\r\n</u><u><i>C</i>                          <i>D</i>\r\n</u><u>E eu quero ficar na tua presença\r\n\r\n</u><u><i>G</i>                   <i>Bm</i>\r\n</u><u>Quando a luz se apagar\r\n</u><u><i>C</i>                   <i>Am</i>\r\n</u><u>Quando a música calar\r\n</u><u><i>G</i>                   <i>Bm</i>\r\n</u><u>Quando o mover passar\r\n</u><u>               <i>C</i>              <i>D</i>\r\n</u><u>Eu só quero o Senhor, só quero o Senhor\r\n\r\n</u><u><i>G</i>      <i>Bm</i>      <i>C</i>           <i>D</i>\r\n</u><u>Jesus, Jesus, Jesus.... só quero o Senhor\r\n</u><u><i>G</i>      <i>Bm</i>      <i>C</i>           <i>D</i>\r\n</u><u>Jesus, Jesus, Jesus.... só quero o Senhor\r\n</u><u><i>G</i>      <i>Bm</i>      <i>C</i>           <i>D</i>\r\n</u><u>Jesus, Jesus, Jesus.... só quero o Senhor\r\n</u><u>        <i>G</i>         <i>Bm</i>\r\n</u><u>Eu só quero o Senhor, só quero o Senhor\r\n</u><u>     <i>C</i>         <i>D</i>\r\n</u><u>Só quero Senhor, só quero Senhor\r\n\r\n</u><u><i>G</i>                   <i>Bm</i>\r\n</u><u> Quando a luz se apagar\r\n</u><u><i>C</i>                  <i>Am</i>\r\n</u><u> Quando a música calar\r\n</u><u><i>G</i>                 <i>Bm</i>\r\n</u><u> Quando o mover passar\r\n</u><u>               <i>C</i>              <i>D</i>\r\n</u><u>Eu só quero o Senhor, só quero o Senhor\r\n</u><u><i>G</i>                   <i>Bm</i>\r\n</u><u> Quando a luz se apagar\r\n</u><u><i>C</i>                  <i>Am</i>\r\n</u><u> Quando a música calar\r\n</u><u><i>G</i>                  <i>Bm</i>\r\n</u><u> Quando o mover passar\r\n</u><u>               <i>C</i>              <i>D</i>\r\n</u><u>Eu só quero o Senhor, só quero o Senhor</u>"
}