{
  "id": "ministerio-zoe-eu-quero-mergulhar-ce6a648603",
  "title": "Eu quero mergulhar",
  "artist": "Ministerio Zoe",
  "collection": "cifras_multi",
  "fileType": "html",
  "key": "E",
  "updatedAt": "2026-04-21T12:45:59.917Z",
  "html": "<u>Intro: <i>Em</i> <i>G/B</i> <i>C9</i> <i>Am</i>\r\n\r\n</u><u><i>Em</i>            <i>G/B</i>       <i>C9</i>       <i>Am</i>\r\n</u><u>Eu quero mergulhar no Teu doce amor\r\n</u><u><i>Em</i>           <i>G/B</i>     <i>C9</i>      <i>Am</i>\r\n</u><u>Como o beija flor que procura a flor\r\n</u><u> <i>Em</i>     <i>G/B</i> <i>C9</i>    <i>Am</i>\r\n</u><u>Mais doce, mais alta, mais\r\n</u><u> <i>Em</i>    <i>G/B</i>      <i>C9</i>          <i>Am</i>\r\n</u><u>longe eu vou te procurar\r\n</u><u><i>G</i>         <i>D/F#</i>     <i>C9</i>\r\n</u><u>Como abelha necessita\r\n</u><u>      <i>Am</i>       <i>Em</i>, <i>G/B</i>, <i>C9</i>, <i>Am</i>\r\n</u><u>do néctar da flor\r\n</u><u><i>G</i>         <i>D/F#</i>    <i>C9</i>    <i>Am</i>\r\n</u><u>Eu não sobreviveria sem Ti\r\n</u><u>       <i>Em</i>, <i>G/B</i>\r\n</u><u>meu Senhor\r\n</u><u>                 <i>C9</i>  <i>Am</i>\r\n</u><u>Sem o Teu doce amor\r\n</u><u><i>Em</i>          <i>G/B</i>\r\n</u><u>Eu sei que sou pequeno\r\n</u><u><i>C9</i>            <i>Am</i>\r\n</u><u>Eu sei que frágil eu sou\r\n</u><u><i>G</i>                 <i>D/F#</i>\r\n</u><u>Mas, eu busco eu caço\r\n</u><u>           <i>C9</i>          <i>Am</i>\r\n</u><u>Eu corro atrás do teu amor\r\n</u><u>           <i>Em</i>             <i>G/B</i>\r\n</u><u>E como a corça clama por água\r\n</u><u>              <i>C9</i>\r\n</u><u>E deixa toda sua segurança\r\n</u><u>              <i>Am</i>\r\n</u><u>para encontrá-la\r\n</u><u>                <i>Em</i>                 <i>G/B</i>\r\n</u><u>Eu abro mão de tudo o que sei, que sou\r\n</u><u>                 <i>C9</i>,<i>Am</i>\r\n</u><u>E clamo por Teu amor\r\n</u><u><i>G</i>         <i>D/F#</i>\r\n</u><u>Eu quero mergulhar\r\n</u><u><i>C9</i>         <i>Am</i>\r\n</u><u>Eu quero me entregar\r\n</u><u><i>Em</i>          <i>G/B</i>             <i>C9</i> <i>Am</i>\r\n</u><u>Eu quero me afogar neste amor</u>"
}