{
  "id": "vencedores-por-cristo-033-quero-transmitir-5f4c72038c",
  "title": "Quero Transmitir",
  "artist": "Vencedores Por Cristo",
  "collection": "cifras_multi",
  "fileType": "html",
  "key": "C",
  "youtubeUrl": "",
  "updatedAt": "2026-04-29T01:40:07.280Z",
  "apiUrl": "/api/songs/vencedores-por-cristo-033-quero-transmitir-5f4c72038c",
  "offlineKey": "mdl-song-vencedores-por-cristo-033-quero-transmitir-5f4c72038c",
  "html": "<span class=\"part\">Intro</span> <i>C</i>  <i>G7</i>\n\n<i>C</i>            <i>Em</i>      <i>F</i>         <i>G</i>\nUma centelha só um grande fogo faz\n    <i>C</i>         <i>Em</i>     <i>F</i>          <i>G</i>\nQueimando ao redor a todos o  calor traz\n  <i>F</i>        <i>G</i>     <i>C</i>   <i>Am</i>  <i>F</i>    <i>G</i>   <i>Em</i>    <i>Am</i>\nO amor de Deus assim é   quando você sentir\n  <i>F</i>          <i>Fm</i>\nO Seu imenso amor sem par\n<i>G</i>               <i>C</i>    <i>G7</i>  <i>C</i>  <i>G7</i>\nVocê vai transmitir\n\n    <i>C</i>       <i>Em</i>       <i>F</i>              <i>G</i>\nA primavera é a mais linda e verde estação\n   <i>C</i>          <i>Em</i>    <i>F</i>             <i>G</i>\nAs aves a cantar a flor que surge do botão\n  <i>F</i>       <i>G</i>      <i>C</i>   <i>Am</i>  <i>F</i>    <i>G</i>   <i>Em</i>      <i>Am</i>\nO amor de Deus assim é    quando você sentir\n  <i>F</i>          <i>Fm</i>\nA todos vai querer contar\n<i>G</i>                <i>C</i>  <i>G7</i>  <i>C</i>  <i>G7</i>\nVocê vai transmitir\n\n     <i>C</i>            <i>Em</i>   <i>F</i>       <i>G</i>\nQuero que você conheça a felicidade\n   <i>C</i>              <i>Em</i>       <i>F</i>        <i>G</i>\nIgual a que encontrei  que é  realidade\n   <i>F</i>     <i>G</i>    <i>C</i>   <i>Am</i>  <i>F</i>   <i>G</i>     <i>Em</i>   <i>Am</i>\nDo alto da montanha   ao mundo vou falar\n     <i>F</i>          <i>Fm</i>\nQue encontrei Jesus Senhor\n   <i>G</i>           <i>C</i>   <i>C7</i>\nE quero transmitir\n\n   <i>F</i>     <i>G</i>    <i>C</i>   <i>Am</i>  <i>F</i>   <i>G</i>    <i>Em</i>    <i>Am</i>\nDo alto da montanha   ao mundo vou falar\n     <i>F</i>         <i>Fm</i>\nQue encontrei Jesus Senhor\n     <i>G</i>            <i>C</i>   <i>F</i>  <i>C</i>\nE queeeero transmitir"
}