{
  "id": "isadora-pompeo-cuido-dos-detalhes-part-andre-e-felipe-8ec9a4d0c9",
  "title": "Cuido Dos Detalhes (part. André e Felipe)",
  "artist": "Isadora Pompeo",
  "collection": "cifras_multi",
  "fileType": "html",
  "key": "G",
  "updatedAt": "2026-04-21T11:46:19.391Z",
  "html": "<u>[Primeira Parte]\r\n\r\n</u><u>[Intro] <i>G</i>  <i>D/F#</i>  <i>Em</i>  <i>C</i>\r\n\r\n</u><u><i>G</i>\r\n</u><u>Madrugadas frias\r\n</u><u><i>D/F#</i>                 <i>Em</i>  <i>C</i>\r\n</u><u>Tantas noites sem dormir\r\n</u><u><i>G</i>\r\n</u><u>O amanhã incerto\r\n</u><u><i>D/F#</i>                 <i>Em</i>   <i>C</i>\r\n</u><u>Pensas que não estou aqui\r\n\r\n</u><u>[Pré-Refrão]\r\n\r\n</u><u>                        <i>Am</i>\r\n</u><u>Mas do teu amanhã eu cuido\r\n</u><u>    <i>C</i>      <i>Em</i>  <i>D</i>\r\n</u><u>Descansa, sossega\r\n</u><u>                       <i>Am</i>\r\n</u><u>Pois eu estou aqui presente\r\n</u><u>  <i>C</i>     <i>D</i>\r\n</u><u>Bem juntinho\r\n\r\n</u><u>[Refrão]\r\n\r\n</u><u>    <i>D</i>                  <i>G</i>\r\n</u><u>Eu estou cuidando de você\r\n</u><u><i>D/F#</i>                   <i>Em</i>\r\n</u><u>Eu estou cuidando de você\r\n</u><u><i>C</i>\r\n</u><u>Pra quê esse medo?\r\n</u><u><i>G</i>\r\n</u><u>Pra que desespero?\r\n</u><u><i>D/F#</i>                   <i>Em</i>\r\n</u><u>Sou eu quem cuido de você!\r\n</u><u>  <i>C</i>                   <i>G</i>\r\n</u><u>Eu estou cuidando de você\r\n</u><u><i>D/F#</i>                   <i>Em</i>\r\n</u><u>Eu estou cuidando de você\r\n</u><u> <i>C</i>\r\n</u><u>Pra quê esse medo?\r\n</u><u> <i>G</i>\r\n</u><u>Pra que desespero?\r\n</u><u><i>D/F#</i>                  <i>Em</i> <i>C</i>\r\n</u><u>Sou eu quem cuido de você!\r\n\r\n</u><u>[Segunda Parte]\r\n\r\n</u><u>  <i>G</i>                    <i>D/F#</i>\r\n</u><u>Deixa comigo tuas ansiedades\r\n</u><u>  <i>Em</i>            <i>C</i>            <i>G</i>\r\n</u><u>Eu vou saber cuidar (saber cuidar)\r\n</u><u>              <i>D/F#</i>\r\n</u><u>Eu não deixo nada na metade\r\n</u><u>  <i>Em</i>             <i>C</i>\r\n</u><u>Tudo eu vou completar\r\n\r\n</u><u>[Pré-Refrão]\r\n\r\n</u><u>                      <i>Am</i>\r\n</u><u>Mas do teu amanhã eu cuido\r\n</u><u>   <i>C</i>       <i>Em</i>  <i>D</i>\r\n</u><u>Descansa, sossega\r\n</u><u>                     <i>Am</i>\r\n</u><u>Pois eu estou aqui presente\r\n</u><u>  <i>C</i>    <i>D</i>\r\n</u><u>Bem juntinho\r\n</u><u>  <i>D</i>                    <i>G</i>\r\n</u><u>Eu estou cuidando de você\r\n</u><u> <i>D/F#</i>                 <i>Em</i>\r\n</u><u>Eu estou cuidando de você\r\n</u><u>  <i>C</i>\r\n</u><u>Pra quê esse medo?\r\n</u><u><i>G</i>\r\n</u><u>Pra que desespero?\r\n</u><u> <i>D/F#</i>                 <i>Em</i>\r\n</u><u>Sou eu quem cuido de você!\r\n</u><u> <i>C</i>                     <i>G</i>\r\n</u><u>Eu estou cuidando de você\r\n</u><u> <i>D/F#</i>                  <i>Em</i>\r\n</u><u>Eu estou cuidando de você\r\n</u><u><i>C</i>\r\n</u><u>Pra quê esse medo?\r\n</u><u><i>G</i>\r\n</u><u>Pra que desespero?\r\n</u><u> <i>D/F#</i>              <i>Em</i>  <i>D</i>\r\n</u><u>Sou eu quem cuido de você!\r\n\r\n</u><u>[Terceira Parte]\r\n\r\n</u><u><i>G</i>\r\n</u><u>Cuido dos detalhes\r\n</u><u><i>D/F#</i>\r\n</u><u>Cuido dos detalhes\r\n</u><u><i>Em</i>              <i>C</i>\r\n</u><u>Cuido do teu coração\r\n</u><u><i>G</i>\r\n</u><u>Pra quê se preocupar?\r\n</u><u><i>D/F#</i>\r\n</u><u>Entrega tudo a mim\r\n</u><u><i>Em</i>         <i>C</i>\r\n</u><u>Pode descansar\r\n</u><u><i>G</i>\r\n</u><u>Cuido dos detalhes\r\n</u><u><i>D/F#</i>\r\n</u><u>Cuido dos detalhes\r\n</u><u><i>Em</i>              <i>C</i>\r\n</u><u>Cuido do teu coração\r\n</u><u><i>G</i>\r\n</u><u>Pra quê se preocupar?\r\n</u><u><i>D/F#</i>\r\n</u><u>Entrega tudo a mim\r\n</u><u><i>Em</i>       <i>C</i>\r\n</u><u>Pode descansar\r\n</u><u>                      <i>G</i>\r\n</u><u>Eu estou cuidando de você\r\n</u><u> <i>D/F#</i>                 <i>Em</i>\r\n</u><u>Eu estou cuidando de você\r\n</u><u> <i>C</i>\r\n</u><u>Pra quê esse medo?\r\n</u><u><i>G</i>\r\n</u><u>Pra que desespero?\r\n</u><u> <i>D/F#</i>                <i>Em</i>  <i>D</i>\r\n</u><u>Sou eu quem cuido de você!</u>"
}