{
  "id": "ministerio-zoe-a-graca-e-a-verdade-690a8960ec",
  "title": "A graça e a verdade",
  "artist": "Ministerio Zoe",
  "collection": "cifras_multi",
  "fileType": "html",
  "key": "E",
  "updatedAt": "2026-04-21T12:45:04.481Z",
  "html": "<u>[Intro]  <i>Em</i>  <i>Am</i>  <i>G</i>  <i>D/F#</i>\r\n</u><u>         <i>Em</i>  <i>Am</i>  <i>G</i>  <i>D/F#</i>\r\n\r\n</u><u>            <i>Em</i>               <i>Am</i>                    <i>G</i>  <i>D/F#</i>\r\n</u><u>Para os que andavam em trevas, brilhou uma grande luz\r\n</u><u>  <i>Em</i>                   <i>Am</i>\r\n</u><u>O verbo se fez carne e habitou entre nós\r\n</u><u>         <i>G</i>              <i>D/F#</i>\r\n</u><u>Cheio de graça e verdade\r\n</u><u>  <i>Em</i>                     <i>D/F#</i>   <i>G</i>\r\n</u><u>A Verdade da Graça é que eu sou filho\r\n</u><u><i>Am</i>                              <i>D7M(9)</i>\r\n</u><u>A Graça da Verdade é que eu não sou mais escravo\r\n</u><u>       <i>Em</i>\r\n</u><u>Eu sou livre\r\n</u><u><i>D/F#</i>  <i>G</i>                    <i>Am</i>            <i>D7M(9)</i>\r\n</u><u>    A verdade me mostrou a graça de ser aceito e amado\r\n\r\n</u><u>( <i>Em</i>  <i>D/F#</i>  <i>G</i>  <i>Am</i>  <i>D7M(9)</i> )\r\n\r\n</u><u><i>Bm</i>           <i>Em</i>                <i>Am</i>               <i>D</i>\r\n</u><u>  A Graça me mostrou a verdade, e o medo já não me domina mais\r\n</u><u><i>Bm</i>                            <i>Em</i>\r\n</u><u>  A incerteza teve um fim, eu descobri quem sou\r\n</u><u>  <i>A/C#</i>\r\n</u><u>E quem Jesus é pra mim\r\n\r\n</u><u><i>Em</i>  <i>D/F#</i>       <i>C/E</i>               <i>Em</i>\r\n</u><u>   Andou entre nós, viveu entre nós\r\n</u><u><i>D/F#</i>          <i>C/E</i>\r\n</u><u>   Se apaixonou, se entregou\r\n</u><u>  <i>Em</i>        <i>D/F#</i>     <i>C/E</i>\r\n</u><u>A morte morreu, e o medo se acovardou\r\n</u><u><i>Em</i>       <i>D/F#</i>     <i>A/C#</i>\r\n</u><u>  Diante da sua vitória\r\n\r\n</u><u>   <i>Em</i>          <i>D/F#</i>  <i>A/C#</i> <i>Em</i>         <i>D/F#</i>  <i>Am</i>\r\n</u><u>Eu sei que Ele voltará, a Graça virá me buscar\r\n</u><u>   <i>Em</i>          <i>D/F#</i>  <i>A/C#</i>         <i>Em</i>      <i>D/F#</i>  <i>A/C#</i>\r\n</u><u>A verdade da eternidade é real, Jesus vem me buscar\r\n\r\n</u><u>   <i>Em</i>          <i>D/F#</i>  <i>A</i>    <i>Em</i>         <i>D/F#</i>  <i>Am</i>\r\n</u><u>Eu sei que Ele voltará, a Graça virá me buscar\r\n</u><u>   <i>Em</i>          <i>D/F#</i>  <i>A</i>            <i>Em</i>      <i>D/F#</i>  <i>A/C#</i>\r\n</u><u>A verdade da eternidade é real, Jesus vem me buscar\r\n\r\n</u><u>( <i>Em</i>  <i>Am</i>  <i>G</i>  <i>D/F#</i> )\r\n\r\n</u><u>            <i>Em</i>               <i>Am</i>                    <i>G</i>  <i>D/F#</i>\r\n</u><u>Para os que andavam em trevas, brilhou uma grande luz\r\n</u><u>  <i>Em</i>                   <i>Am</i>\r\n</u><u>O verbo se fez carne e habitou entre nós\r\n</u><u>         <i>G</i>              <i>D/F#</i>\r\n</u><u>Cheio de graça e verdade\r\n</u><u>  <i>Em</i>                     <i>D/F#</i>   <i>G</i>\r\n</u><u>A Verdade da Graça é que eu sou filho\r\n</u><u><i>Am</i>                              <i>D7M(9)</i>\r\n</u><u>A Graça da Verdade é que eu não sou mais escravo\r\n</u><u>       <i>Em</i>\r\n</u><u>Eu sou livre\r\n</u><u><i>D/F#</i>  <i>G</i>                    <i>Am</i>            <i>D7M(9)</i>\r\n</u><u>    A verdade me mostrou a graça de ser aceito e amado\r\n\r\n</u><u>( <i>Em</i>  <i>D/F#</i>  <i>G</i>  <i>Am</i>  <i>D7M(9)</i> )\r\n\r\n</u><u><i>Bm</i>           <i>Em</i>                <i>Am</i>               <i>D</i>\r\n</u><u>  A Graça me mostrou a verdade, e o medo já não me domina mais\r\n</u><u><i>Bm</i>                            <i>Em</i>\r\n</u><u>  A incerteza teve um fim, eu descobri quem sou\r\n</u><u>  <i>A/C#</i>\r\n</u><u>E quem Jesus é pra mim\r\n\r\n</u><u><i>Em</i>  <i>D/F#</i>       <i>C/E</i>               <i>Em</i>\r\n</u><u>   Andou entre nós, viveu entre nós\r\n</u><u><i>D/F#</i>          <i>C/E</i>\r\n</u><u>   Se apaixonou, se entregou\r\n</u><u>  <i>Em</i>        <i>D/F#</i>     <i>C/E</i>\r\n</u><u>A morte morreu, e o medo se acovardou\r\n</u><u><i>Em</i>       <i>D/F#</i>     <i>A/C#</i>\r\n</u><u>  Diante da sua vitória\r\n\r\n</u><u>   <i>Em</i>          <i>D/F#</i>  <i>A/C#</i> <i>Em</i>         <i>D/F#</i>  <i>Am</i>\r\n</u><u>Eu sei que Ele voltará, a Graça virá me buscar\r\n</u><u>   <i>Em</i>          <i>D/F#</i>  <i>A/C#</i>         <i>Em</i>      <i>D/F#</i>  <i>A/C#</i>\r\n</u><u>A verdade da eternidade é real, Jesus vem me buscar\r\n\r\n</u><u>   <i>Em</i>          <i>D/F#</i>  <i>A/C#</i> <i>Em</i>         <i>D/F#</i>  <i>Am</i>\r\n</u><u>Eu sei que Ele voltará, a Graça virá me buscar\r\n</u><u>   <i>Em</i>          <i>D/F#</i>  <i>A/C#</i>         <i>Em</i>      <i>D/F#</i>  <i>A/C#</i>\r\n</u><u>A verdade da eternidade é real, Jesus vem me buscar\r\n\r\n</u><u>( <i>Em</i>  <i>D/F#</i>  <i>Am</i> )\r\n</u><u>( <i>Em</i>  <i>D/F#</i>  <i>Am</i> )\r\n\r\n</u><u>       <i>Em</i>           <i>D/F#</i>  <i>C/G</i>               <i>Em</i>  <i>D/F#</i>  <i>C/G</i>\r\n</u><u>E eu o verei face a face, assim como Ele é\r\n</u><u>      <i>Em</i>     <i>D/F#</i>   <i>C/G</i>\r\n</u><u>Correrei com Ele pelos campos brancos\r\n</u><u><i>Em</i>     <i>D/F#</i>   <i>C/G</i>                         <i>Em</i>  <i>D/F#</i>  <i>C/G</i>\r\n</u><u>  Abraçarei o meu amado, eu brincarei com Ele\r\n</u><u>    <i>Em</i>     <i>D/F#</i>   <i>C/G</i>                      <i>Em</i>  <i>D/F#</i>  <i>C/G</i>\r\n</u><u>Sentirei o seu perfume, eu dormirei em seu colo\r\n\r\n</u><u>Enquanto Ele me faz cafuné\r\n</u><u><i>Em</i>     <i>D/F#</i>   <i>C/G</i>\r\n</u><u>  A eternidade está sorrindo pra mim\r\n</u><u><i>Em</i>     <i>D/F#</i>   <i>C/G</i>\r\n</u><u>No meu lar eu posso descaçar enfim\r\n\r\n</u><u>( <i>Em</i>  <i>D/F#</i>  <i>C/G</i> )\r\n\r\n</u><u>   <i>Em</i>          <i>D/F#</i>  <i>C/G</i>   <i>Em</i>         <i>D/F#</i>  <i>Am</i>\r\n</u><u>Eu sei que Ele voltará, a Graça virá me buscar\r\n</u><u>   <i>Em</i>          <i>D/F#</i>  <i>C/G</i>            <i>Em</i>      <i>D/F#</i>  <i>Am</i>\r\n</u><u>A verdade da eternidade é real, Jesus vem me buscar</u>"
}